compneuro/__init__.py
compneuro/kernels/__init__.py
compneuro/kernels/factory/rate.py
compneuro/signal.py
compneuro/simulate.py
compneuro/testing.py
compneuro/visualize.py
lcg_neuro_compneuro-0.1.0.dist-info/LICENSE.txt
lcg_neuro_compneuro-0.1.0.dist-info/WHEEL
lcg_neuro_compneuro-0.1.0.dist-info/METADATA
lcg_neuro_compneuro-0.1.0.dist-info/RECORD
