Metadata-Version: 2.1
Name: lcg-neuro-compneuro
Version: 0.1.0
Summary: Computational neuroscience library for Python
Home-page: https://lcg.gitlab.io/neuro/python-compneuro
License: MIT
Author: Pedro Asad
Author-email: pasad@lcg.ufrj.br
Requires-Python: >=3.6,<4.0
Classifier: License :: OSI Approved :: MIT License
Classifier: Programming Language :: Python :: 3
Classifier: Programming Language :: Python :: 3.6
Classifier: Programming Language :: Python :: 3.7
Provides-Extra: all
Provides-Extra: matplotlib
Requires-Dist: matplotlib (>=3.1,<4.0); extra == "all" or extra == "matplotlib"
Requires-Dist: scipy (>=1.3,<2.0)
Project-URL: Documentation, https://lcg.gitlab.io/neuro/python-compneuro
Project-URL: Repository, https://gitlab.com/lcg/neuro/python-compneuro
